pry.py
pry.py-0.1.1.dist-info/METADATA
pry.py-0.1.1.dist-info/RECORD
pry.py-0.1.1.dist-info/WHEEL
pry.py-0.1.1.dist-info/top_level.txt
pry.py-0.1.1.dist-info/zip-safe
