Metadata-Version: 2.1
Name: pry.py
Version: 0.1.1
Summary: Pry ruby-like interactive shell, written in Python
Home-page: https://github.com/Mic92/pry.py
Author: Joerg Thalheim
Author-email: joerg@thaleheim.io
License: MIT License
Platform: UNKNOWN
Classifier: Development Status :: 5 - Production/Stable
Classifier: Intended Audience :: Developers
Classifier: License :: OSI Approved :: MIT License
Classifier: Natural Language :: English
Classifier: Operating System :: OS Independent
Classifier: Programming Language :: Python
Classifier: Programming Language :: Python :: 3
Classifier: Topic :: Software Development :: Libraries :: Python Modules
Classifier: Topic :: Software Development :: Debuggers
